tests/__init__.py
tests/test_countries.py
tests/test_events.py
tests/test_leagues.py
tests/test_requests.py
tests/test_search.py
tests/test_sports.py
tests/test_teams.py
thesportsdb/__init__.py
thesportsdb/countries.py
thesportsdb/events.py
thesportsdb/leagues.py
thesportsdb/players.py
thesportsdb/requests.py
thesportsdb/search.py
thesportsdb/settings.py
thesportsdb/sports.py
thesportsdb/teams.py
thesportsdb-0.3.1.dist-info/licenses/LICENSE
thesportsdb-0.3.1.dist-info/METADATA
thesportsdb-0.3.1.dist-info/WHEEL
thesportsdb-0.3.1.dist-info/top_level.txt
thesportsdb-0.3.1.dist-info/RECORD
